egasub/__init__.py
egasub/cli.py
egasub/utils.py
egasub/exceptions.py
egasub/ega/__init__.py
egasub/ega/data/enums/library_strategies.json
egasub/ega/data/enums/genders.json
egasub/ega/data/enums/library_sources.json
egasub/ega/data/enums/instrument_models.json
egasub/ega/data/enums/file_types.json
egasub/ega/data/enums/reference_chromosomes.json
egasub/ega/data/enums/experiment_types.json
egasub/ega/data/enums/case_control.json
egasub/ega/data/enums/library_selections.json
egasub/ega/data/enums/analysis_types.json
egasub/ega/data/enums/dataset_types.json
egasub/ega/data/enums/library_layouts.json
egasub/ega/data/enums/reference_genomes.json
egasub/ega/data/enums/study_types.json
egasub/ega/services/__init__.py
egasub/ega/services/ftp/__init__.py
egasub/ega/entities/run.py
egasub/ega/entities/sample_reference.py
egasub/ega/entities/attribute.py
egasub/ega/entities/analysis.py
egasub/ega/entities/chromosome_reference.py
egasub/ega/entities/custom_tag.py
egasub/ega/entities/dac.py
egasub/ega/entities/submission.py
egasub/ega/entities/policy.py
egasub/ega/entities/__init__.py
egasub/ega/entities/dataset.py
egasub/ega/entities/experiment.py
egasub/ega/entities/file.py
egasub/ega/entities/sample.py
egasub/ega/entities/submission_subset_data.py
egasub/ega/entities/ega_enums.py
egasub/ega/entities/study.py
egasub/ega/entities/contact.py
egasub/ega/entities/dataset_link.py
egasub/icgc/__init__.py
egasub/icgc/services/__init__.py
egasub/submission/submit.py
egasub/submission/__init__.py
egasub/submission/init_submission_dir.py
egasub/submission/init.py
egasub/submission/submitter.py
egasub/submission/status.py
egasub/submission/submittable/unaligned.py
egasub/submission/submittable/alignment.py
egasub/submission/submittable/__init__.py
egasub/submission/submittable/variation.py
egasub/submission/submittable/base.py
egasub/submission/metadata_template/variation/analysis.yaml
egasub-0.1.0rc14.dist-info/RECORD
egasub-0.1.0rc14.dist-info/metadata.json
egasub-0.1.0rc14.dist-info/WHEEL
egasub-0.1.0rc14.dist-info/entry_points.txt
egasub-0.1.0rc14.dist-info/DESCRIPTION.rst
egasub-0.1.0rc14.dist-info/top_level.txt
egasub-0.1.0rc14.dist-info/METADATA
