Metadata-Version: 2.0
Name: egasub
Version: 0.1.0rc14
Summary: ICGC tool for assisting EGA data submission
Home-page: https://github.com/icgc-dcc/egasub
Author: UNKNOWN
Author-email: UNKNOWN
License: GPL-3.0
Platform: UNKNOWN
Requires-Dist: click (>=6.1)
Requires-Dist: PyYAML (>=3.10)
Requires-Dist: requests (>=2.10)
